src/VersionUtil.py
src/__init__.py
ProjectREMLA23Team09Lib-0.0.1.dist-info/METADATA
ProjectREMLA23Team09Lib-0.0.1.dist-info/WHEEL
ProjectREMLA23Team09Lib-0.0.1.dist-info/top_level.txt
ProjectREMLA23Team09Lib-0.0.1.dist-info/RECORD
